[
	{
		"id": "148772a8-9702-4c57-93a3-41734ac14d5a",
		"timestamp": "12/05/2022, 9:43:48 pm",
		"nombre": "Campera",
		"descripcion": "Campera para que no te cagues de frio",
		"codigo": "C665",
		"precio": 995.45,
		"thumbnail": "https://picsum.photos/400",
		"stock": 6
	},
	{
		"id": "148772a8-9702-4c57-93a3-41734ac14d5a",
		"timestamp": "12/05/2022, 9:14:58 pm",
		"nombre": "Chinelas",
		"descripcion": "Chinelas para el calor papá!",
		"codigo": "C485",
		"precio": 200,
		"thumbnail": "https://picsum.photos/400",
		"stock": 9
	}
]